Workbook

Sheet Comps_Val
B11: Figures in Crores
B12: Comparable Company Valuation
D14: Market Data | J14: Financials | N14: Valuation
B15: Company | C15: Ticker | D15: Share Price | E15: Shares Outstanding | F15: Equity Value | G15: Net Debt | H15: Enterprise Value | J15: Revenue | K15: EBITDA | L15: Net Income | N15: EV/Revenue | O15: EV/EBITDA | P15: P/E
B17: =Sheet2!$C$7 -> Cipla | C17: CIPLA | D17: =Sheet2!D7 -> 1327 | E17: =Sheet2!E7 -> 80.78 | F17: =D17*E17 -> 107195.06 | G17: =Sheet2!I7 -> -332.47 | H17: =Sheet2!J7 -> 106862.59 | J17: =Sheet2!K7 -> 28351.08 | K17: =Sheet2!N7 -> 7488.85 | L17: =Sheet2!O3 -> 10952.92 | N17: =$H17/J17 -> 3.7692599 | O17: =$H17/K17 -> 14.269559 | P17: =F17/L17 -> 9.7868934
B18: =Sheet2!C3 -> Sun Pharma.Inds. | C18: SUNPHARMA | D18: =Sheet2!D3 -> 1787 | E18: =Sheet2!E3 -> 239.93 | F18: =D18*E18 -> 428754.91 | G18: =Sheet2!I3 -> -6116.52 | H18: =Sheet2!J3 -> 422638.39 | J18: =Sheet2!K3 -> 56809.09 | K18: =Sheet2!N3 -> 19619.38 | L18: =Sheet2!O4 -> 2479 | N18: =$H18/J18 -> 7.4396261 | O18: =$H18/K18 -> 21.541883 | P18: =F18/L18 -> 172.95478
B19: =Sheet2!C4 -> Divi's Lab. | C19: DIVISLAB | D19: =Sheet2!D4 -> 6368 | E19: =Sheet2!E4 -> 26.55 | F19: =D19*E19 -> 169070.4 | G19: =Sheet2!I4 -> -3625 | H19: =Sheet2!J4 -> 165445.4 | J19: =Sheet2!K4 -> 10314 | K19: =Sheet2!N4 -> 3831 | L19: =Sheet2!O5 -> 2272 | N19: =$H19/J19 -> 16.040857 | O19: =$H19/K19 -> 43.185957 | P19: =F19/L19 -> 74.414789
B20: =Sheet2!C5 -> Torrent Pharma. | C20: TORNTPHARM | D20: =Sheet2!D5 -> 4347.65 | E20: =Sheet2!E5 -> 33.84 | F20: =D20*E20 -> 147124.48 | G20: =Sheet2!I5 -> 2242.54 | H20: =Sheet2!J5 -> 149367.02 | J20: =Sheet2!K5 -> 12742 | K20: =Sheet2!N5 -> 4072 | L20: =Sheet2!O6 -> 5523 | N20: =$H20/J20 -> 11.722415 | O20: =$H20/K20 -> 36.681487 | P20: =F20/L20 -> 26.638507
B21: =Sheet2!C6 -> Dr Reddy's Labs | C21: DRREDY | D21: =Sheet2!D6 -> 1315.2 | E21: =Sheet2!E6 -> 83.46 | F21: =D21*E21 -> 109766.59 | G21: =Sheet2!I6 -> 3393.8 | H21: =Sheet2!J6 -> 113160.39 | J21: =Sheet2!K6 -> 34682.2 | K21: =Sheet2!N6 -> 9488.3 | L21: =Sheet2!O7 -> 4533.37 | N21: =$H21/J21 -> 3.2627801 | O21: =$H21/K21 -> 11.926308 | P21: =F21/L21 -> 24.213023
B22: =Sheet2!C8 -> Lupin | C22: LUPIN | D22: =Sheet2!D8 -> 2334 | E22: =Sheet2!E8 -> 45.7 | F22: =D22*E22 -> 106663.8 | G22: =Sheet2!I8 -> 3074.67 | H22: =Sheet2!J8 -> 109738.47 | J22: =Sheet2!K8 -> 26150.5 | K22: =Sheet2!N8 -> 7992.28 | L22: =Sheet2!O8 -> 4669.18 | N22: =$H22/J22 -> 4.1964196 | O22: =$H22/K22 -> 13.730559 | P22: =F22/L22 -> 22.844225
B23: =Sheet2!C9 -> Zydus Lifesci. | C23: ZYDUSLIFE | D23: =Sheet2!D9 -> 914.45 | E23: =Sheet2!E9 -> 100.62 | F23: =D23*E23 -> 92011.959 | G23: =Sheet2!I9 -> 6679.3 | H23: =Sheet2!J9 -> 98691.259 | J23: =Sheet2!K9 -> 26089.3 | K23: =Sheet2!N9 -> 8502.1 | L23: =Sheet2!O9 -> 5026.2 | N23: =$H23/J23 -> 3.7828251 | O23: =$H23/K23 -> 11.607869 | P23: =F23/L23 -> 18.306466
B24: =Sheet2!C10 -> Mankind Pharma | C24: MANKIND | D24: =Sheet2!D10 -> 2224.55 | E24: =Sheet2!E10 -> 41.28 | F24: =D24*E24 -> 91829.424 | G24: =Sheet2!I10 -> 7814.15 | H24: =Sheet2!J10 -> 99643.574 | J24: =Sheet2!K10 -> 13914.08 | K24: =Sheet2!N10 -> 3877.57 | L24: =Sheet2!O10 -> 1803.33 | N24: =$H24/J24 -> 7.1613484 | O24: =$H24/K24 -> 25.697428 | P24: =F24/L24 -> 50.922141
B25: =Sheet2!C11 -> Aurobindo Pharma | C25: AUROPHARMA | D25: =Sheet2!D11 -> 1226.7 | E25: =Sheet2!E11 -> 58.08 | F25: =D25*E25 -> 71246.736 | G25: =Sheet2!I11 -> -440.99 | H25: =Sheet2!J11 -> 70805.746 | J25: =Sheet2!K11 -> 33181.86 | K25: =Sheet2!N11 -> 7366.49 | L25: =Sheet2!O11 -> 3484.96 | N25: =$H25/J25 -> 2.1338691 | O25: =$H25/K25 -> 9.6118702 | P25: =F25/L25 -> 20.444061
B26: =Sheet2!C12 -> Alkem Lab | C26: ALKEM | D26: =Sheet2!D12 -> 5552.2 | E26: =Sheet2!E12 -> 11.96 | F26: =D26*E26 -> 66404.312 | G26: =Sheet2!I12 -> 792.52 | H26: =Sheet2!J12 -> 67196.832 | J26: =Sheet2!K12 -> 14252.7 | K26: =Sheet2!N12 -> 3408.35 | L26: =Sheet2!O12 -> 2422.44 | N26: =$H26/J26 -> 4.7146739 | O26: =$H26/K26 -> 19.715356 | P26: =F26/L26 -> 27.41216
B28: High | N28: =MAX(N17:N26) -> 16.040857 | O28: =MAX(O17:O26) -> 43.185957 | P28: =MAX(P17:P26) -> 172.95478
B29: 75th Percentile | N29: =QUARTILE(N17:N26,) -> 2.1338691 | O29: =QUARTILE(O17:O26,) -> 9.6118702 | P29: =QUARTILE(P17:P26,) -> 9.7868934
B30: Average | N30: =AVERAGE(N17:N26) -> 6.4224075 | O30: =AVERAGE(O17:O26) -> 20.796828 | P30: =AVERAGE(P17:P26) -> 44.793705
B31: Median | N31: =MEDIAN(N17:N26) -> 4.4555467 | O31: =MEDIAN(O17:O26) -> 16.992457 | P31: =MEDIAN(P17:P26) -> 25.425765
B32: 25th Percentile | N32: =QUARTILE(N17:N26,) -> 2.1338691 | O32: =QUARTILE(O17:O26,) -> 9.6118702 | P32: =QUARTILE(P17:P26,) -> 9.7868934
B33: Low | N33: =MIN(N17:N26) -> 2.1338691 | O33: =MIN(O17:O26) -> 9.6118702 | P33: =MIN(P17:P26) -> 9.7868934
B35: Cipla Comparable Valuation | N35: EV/Revenue | O35: EV/EBITDA | P35: P/E
B37: Implied Enterprise Value | N37: =N$31*J17 -> 126319.56 | O37: =O$31*K17 -> 127253.97 | P37: =P39+P38 -> 278153.9
B38: Net Debt | N38: =$G$17 -> -332.47 | O38: =$G$17 -> -332.47 | P38: =$G$17 -> -332.47
B39: Implied Market Value | N39: =N37-N38 -> 126652.03 | O39: =O37-O38 -> 127586.44 | P39: =P31*L17 -> 278486.37
B40: Shares Outstandings | N40: =$E$17 -> 80.78 | O40: =$E$17 -> 80.78 | P40: =$E$17 -> 80.78
B42: Implied Value Per Share | N42: =N39/N40 -> 1567.8637 | O42: =O39/O40 -> 1579.431 | P42: =P39/P40 -> 3447.4668
B44: Source: Screener.in
N45: =IF(N42>$D$17, "Undervalued","Overvalued") -> Undervalued | O45: =IF(O42>$D$17, "Undervalued","Overvalued") -> Undervalued | P45: =IF(P42>$D$17, "Undervalued","Overvalued") -> Undervalued

Sheet Sheet2
B2: S.No. | C2: Name | D2: CMP Rs. | E2: No. Eq. Shares Cr. | F2: Market Value/Cap | G2: Debt Rs.Cr. | H2: Cash End Rs.Cr. | I2: Net Debt | J2: EV | K2: Sales Rs.Cr. | L2: EBIT 12M Rs.Cr. | M2: Dep 12M Rs.Cr. | N2: EBITDA | O2: NP 12M Rs.Cr
B3: 1 | C3: Sun Pharma.Inds. | D3: 1787 | E3: 239.93 | F3: =D3*E3 -> 428754.91 | G3: 5215.1 | H3: 11331.62 | I3: =G3-H3 -> -6116.52 | J3: =F3+G3-H3 -> 422638.39 | K3: 56809.09 | L3: 16793.21 | M3: 2826.17 | N3: =L3+M3 -> 19619.38 | O3: 10952.92
B4: 2 | C4: Divi's Lab. | D4: 6368 | E4: 26.55 | F4: =D4*E4 -> 169070.4 | G4: 90 | H4: 3715 | I4: =G4-H4 -> -3625 | J4: =F4+G4-H4 -> 165445.4 | K4: 10314 | L4: 3381 | M4: 450 | N4: =L4+M4 -> 3831 | O4: 2479
B5: 3 | C5: Torrent Pharma. | D5: 4347.65 | E5: 33.84 | F5: =D5*E5 -> 147124.48 | G5: 2822 | H5: 579.46 | I5: =G5-H5 -> 2242.54 | J5: =F5+G5-H5 -> 149367.02 | K5: 12742 | L5: 3260 | M5: 812 | N5: =L5+M5 -> 4072 | O5: 2272
B6: 4 | C6: Dr Reddy's Labs | D6: 1315.2 | E6: 83.46 | F6: =D6*E6 -> 109766.59 | G6: 5854 | H6: 2460.2 | I6: =G6-H6 -> 3393.8 | J6: =F6+G6-H6 -> 113160.39 | K6: 34682.2 | L6: 7531.9 | M6: 1956.4 | N6: =L6+M6 -> 9488.3 | O6: 5523
B7: 5 | C7: Cipla | D7: 1327 | E7: 80.78 | F7: =D7*E7 -> 107195.06 | G7: 467.37 | H7: 799.84 | I7: =G7-H7 -> -332.47 | J7: =F7+G7-H7 -> 106862.59 | K7: 28351.08 | L7: 6352.06 | M7: 1136.79 | N7: =L7+M7 -> 7488.85 | O7: 4533.37
B8: 6 | C8: Lupin | D8: 2334 | E8: 45.7 | F8: =D8*E8 -> 106663.8 | G8: 6217 | H8: 3142.33 | I8: =G8-H8 -> 3074.67 | J8: =F8+G8-H8 -> 109738.47 | K8: 26150.5 | L8: 6670.39 | M8: 1321.89 | N8: =L8+M8 -> 7992.28 | O8: 4669.18
B9: 7 | C9: Zydus Lifesci. | D9: 914.45 | E9: 100.62 | F9: =D9*E9 -> 92011.959 | G9: 9636.1 | H9: 2956.8 | I9: =G9-H9 -> 6679.3 | J9: =F9+G9-H9 -> 98691.259 | K9: 26089.3 | L9: 7364.6 | M9: 1137.5 | N9: =L9+M9 -> 8502.1 | O9: 5026.2
B10: 8 | C10: Mankind Pharma | D10: 2224.55 | E10: 41.28 | F10: =D10*E10 -> 91829.424 | G10: 8368.65 | H10: 554.5 | I10: =G10-H10 -> 7814.15 | J10: =F10+G10-H10 -> 99643.574 | K10: 13914.08 | L10: 2983.6 | M10: 893.97 | N10: =L10+M10 -> 3877.57 | O10: 1803.33
B11: 9 | C11: Aurobindo Pharma | D11: 1226.7 | E11: 58.08 | F11: =D11*E11 -> 71246.736 | G11: 7794.5 | H11: 8235.49 | I11: =G11-H11 -> -440.99 | J11: =F11+G11-H11 -> 70805.746 | K11: 33181.86 | L11: 5622.44 | M11: 1744.05 | N11: =L11+M11 -> 7366.49 | O11: 3484.96
B12: 10 | C12: Alkem Lab | D12: 5552.2 | E12: 11.96 | F12: =D12*E12 -> 66404.312 | G12: 2355.6 | H12: 1563.08 | I12: =G12-H12 -> 792.52 | J12: =F12+G12-H12 -> 67196.832 | K12: 14252.7 | L12: 3019.56 | M12: 388.79 | N12: =L12+M12 -> 3408.35 | O12: 2422.44
